[{"id":1,"name":"一心","saleman":"劉天王"},{"id":2,"name":"小陽堂","saleman":"柯吉霸"},{"id":3,"name":"德菖","saleman":"黎國明"},{"id":4,"name":"涵合","saleman":"曾麗亥"},{"id":5,"name":"普三","saleman":"林美麗"},{"id":6,"name":"光權","saleman":"艾逮丸"},{"id":7,"name":"掬花","saleman":"趙飛燕"},{"id":8,"name":"宏仁","saleman":"郝欣仁"},{"id":9,"name":"康堡","saleman":"孟庭亭"},{"id":10,"name":"德級","saleman":"蘇涵蘊"},{"id":11,"name":"玉成","saleman":"張瑾雯"},{"id":12,"name":"記成","saleman":"洪慮登"},{"id":13,"name":"利利","saleman":"吳添涼"},{"id":14,"name":"金美蘭","saleman":"吳仁幸"},{"id":15,"name":"佳佳","saleman":"曾艾梅"},{"id":16,"name":"為全","saleman":"郝布豪"},{"id":17,"name":"桶一","saleman":"奈安內"},{"id":18,"name":"正一","saleman":"盧小小"},{"id":19,"name":"小坊","saleman":"艾道泥"},{"id":20,"name":"義美美","saleman":"花布丸"},{"id":21,"name":"小噹","saleman":"曾艾花"},{"id":22,"name":"百達","saleman":"吳宗將"},{"id":23,"name":"力錦","saleman":"柯玲芬"},{"id":24,"name":"生活妙","saleman":"郝享枯"},{"id":25,"name":"東黃海","saleman":"艾扣扣"},{"id":26,"name":"日正","saleman":"鐵迪丸"},{"id":27,"name":"日日通","saleman":"洪隆國"},{"id":28,"name":"大鈺","saleman":"萬塗利"},{"id":29,"name":"順成","saleman":"魏繩墨"}]